ANNOUNCE
AUTHORS
CHANGES
LICENSE
MANIFEST.in
README.rst
requirements.txt
setup.py
urlpathlib/__init__.py
urlpathlib/urlpath.py
urlpathlib/utils.py
urlpathlib.egg-info/PKG-INFO
urlpathlib.egg-info/SOURCES.txt
urlpathlib.egg-info/dependency_links.txt
urlpathlib.egg-info/not-zip-safe
urlpathlib.egg-info/top_level.txt
urlpathlib/schemes/__init__.py
urlpathlib/schemes/file.py
urlpathlib/schemes/http.py