Metadata-Version: 1.1
Name: urlpathlib
Version: 0.0.1
Summary: urlpathlib
Home-page: UNKNOWN
Author: Morgan Delahaye-Prat
Author-email: mdp@sillog.net
License: BSD
Platform: any
Classifier: Development Status :: 4 - Beta
Classifier: Programming Language :: Python
Classifier: Programming Language :: Python :: 3
Classifier: Programming Language :: Python :: 3.5
Classifier: Programming Language :: Python :: 3.6
